jiujitsu/__init__.py
jiujitsu/bpFileSystem.py
jiujitsu/bpInterpreter.py
jiujitsu/bpInterpreterBase.py
jiujitsu/bpPrimitives.py
jiujitsu/jInterpreter.py
jiujitsu/jNode.py
jiujitsu/jParser.py
jiujitsu/jRecord.py
jiujitsu/test/__init__.py
jiujitsu/test/test_bpInterpreterBase.py
jiujitsu/test/test_bpPrimitives.py
jiujitsu/test/test_jInterpreter.py
jiujitsu/test/test_jParser.py
jiujitsu-0.6.dist-info/METADATA
jiujitsu-0.6.dist-info/WHEEL
jiujitsu-0.6.dist-info/entry_points.txt
jiujitsu-0.6.dist-info/top_level.txt
jiujitsu-0.6.dist-info/RECORD
