Metadata-Version: 2.1
Name: jiujitsu
Version: 0.6
Summary: A custom bash interpreter for malware execution
Home-page: https://github.com/BlankCanvasStudio/jiujitsu
Author: Spencer Stingley
Author-email: sstingle@usc.edu
Keywords: bash,parsing,interpreter,analysis,malware
Classifier: Programming Language :: Python :: 3
Classifier: Operating System :: OS Independent
Requires-Python: >=3.6
Requires-Dist: bashlex
Requires-Dist: bashparser
